django_recent_objects-0.1.1.dist-info/licenses/LICENSE
recent_objects/__init__.py
recent_objects/recent_objects.py
django_recent_objects-0.1.1.dist-info/METADATA
django_recent_objects-0.1.1.dist-info/WHEEL
django_recent_objects-0.1.1.dist-info/top_level.txt
django_recent_objects-0.1.1.dist-info/RECORD
