Metadata-Version: 2.4
Name: django_recent_objects
Version: 0.1.1
Summary: Recent objects fetching utilities
Home-page: https://github.com/matthiask/django-recent-objects/
Author: Matthias Kestenholz
Author-email: mk@feinheit.ch
License: BSD-3-Clause
Platform: OS Independent
Classifier: Development Status :: 5 - Production/Stable
Classifier: Environment :: Web Environment
Classifier: Framework :: Django
Classifier: Intended Audience :: Developers
Classifier: License :: OSI Approved :: BSD License
Classifier: Operating System :: OS Independent
Classifier: Programming Language :: Python
Classifier: Programming Language :: Python :: 3
Classifier: Programming Language :: Python :: 3 :: Only
Classifier: Programming Language :: Python :: 3.9
Classifier: Programming Language :: Python :: 3.10
Classifier: Topic :: Internet :: WWW/HTTP :: Dynamic Content
Classifier: Topic :: Software Development
Classifier: Topic :: Software Development :: Libraries :: Application Frameworks
Requires-Python: >=3.9
License-File: LICENSE
Requires-Dist: Django>=3.2
Provides-Extra: tests
Requires-Dist: coverage; extra == "tests"
Dynamic: license-file
